{
  "dishes": [
    {
      "id": 0,
      "name": "Ginger Burger",
      "image": "images/0burger.jpg",
      "category": "meal",
      "label": "Hot",
      "price": "199",
      "featured": true,
      "description": "This chicken burger gets an Asian-flavor twist with ginger and garlic. It's topped off with a fabulous coleslaw. If you like, serve the coleslaw as a side for grilled items, like chicken breasts, fish fillets or chops"
    },
    {
      "id": 1,
      "name": "BBQ Chicken Pizza",
      "image": "images/1pizza.jpg",
      "category": "meal",
      "label": "",
      "price": "599",
      "featured": false,
      "description": "BBQ chicken pizza with tangy BBQ sauce, chicken, and red onion. Gouda cheese gives the homemade pizza the most delicious smoky flavor and cilantro adds a touch of freshness. My pizza dough recipe makes enough for two 12-inch pizzas, so you can freeze half for later. It’s an easy thick-style pizza crust with unbeatable flavor."
    },
    {
      "id": 2,
      "name": "French Fries",
      "image": "images/2fries.jpg",
      "category": "appetizer",
      "label": "New",
      "price": "120",
      "featured": false,
      "description": "These are deep-fried, very thin, salted slices of potato that are usually served at room temperature. French fries have numerous variants, from thick-cut to shoestring, crinkle, curly and many other names."
    },
    {
      "id": 3,
      "name": "Cheese Cake",
      "image": "images/3cake.jpg",
      "category": "dessert",
      "label": "",
      "price": "170",
      "featured": false,
      "description": "A delectable, semi-sweet New York Style Cheese Cake, with cracker crust and spiced with Indian cardamoms"
    }
  ],
  "comments": [
    {
      "dishId": 0,
      "id": 0,
      "rating": 5,
      "comment": "Imagine all the eatables, living in conFusion!",
      "author": "Shanto",
      "date": "2018-10-16T17:57:28.556094Z"
    },
    {
      "dishId": 0,
      "id": 1,
      "rating": 4,
      "comment": "Sends anyone to heaven, I wish I could get my mother-in-law to eat it!",
      "author": "Karim",
      "date": "2017-09-05T17:57:28.556094Z"
    },
    {
      "dishId": 0,
      "id": 2,
      "rating": 3,
      "comment": "Eat it, just eat it!",
      "author": "Moinul",
      "date": "2019-02-13T17:57:28.556094Z"
    },
    {
      "dishId": 0,
      "id": 3,
      "rating": 4,
      "comment": "Ultimate, Reaching for the stars!",
      "author": "Rahat",
      "date": "2017-12-02T17:57:28.556094Z"
    },
    {
      "dishId": 0,
      "id": 4,
      "rating": 2,
      "comment": "It's your birthday, we're gonna party!",
      "author": "Rony",
      "date": "2019-12-02T17:57:28.556094Z"
    },
    {
      "dishId": 1,
      "id": 5,
      "rating": 5,
      "comment": "Imagine all the eatables, living in conFusion!",
      "author": "Shanto",
      "date": "2018-10-16T17:57:28.556094Z"
    },
    {
      "dishId": 1,
      "id": 6,
      "rating": 4,
      "comment": "Sends anyone to heaven, I wish I could get my mother-in-law to eat it!",
      "author": "Karim",
      "date": "2017-09-05T17:57:28.556094Z"
    },
    {
      "dishId": 1,
      "id": 7,
      "rating": 3,
      "comment": "Eat it, just eat it!",
      "author": "Moinul",
      "date": "2019-02-13T17:57:28.556094Z"
    },
    {
      "dishId": 1,
      "id": 8,
      "rating": 4,
      "comment": "Ultimate, Reaching for the stars!",
      "author": "Rahat",
      "date": "2017-12-02T17:57:28.556094Z"
    },
    {
      "dishId": 1,
      "id": 9,
      "rating": 2,
      "comment": "It's your birthday, we're gonna party!",
      "author": "Rony",
      "date": "2019-12-02T17:57:28.556094Z"
    },
    {
      "dishId": 2,
      "id": 10,
      "rating": 5,
      "comment": "Imagine all the eatables, living in conFusion!",
      "author": "Shanto",
      "date": "2018-10-16T17:57:28.556094Z"
    },
    {
      "dishId": 2,
      "id": 11,
      "rating": 4,
      "comment": "Sends anyone to heaven, I wish I could get my mother-in-law to eat it!",
      "author": "Karim",
      "date": "2017-09-05T17:57:28.556094Z"
    },
    {
      "dishId": 2,
      "id": 12,
      "rating": 3,
      "comment": "Eat it, just eat it!",
      "author": "Moinul",
      "date": "2019-02-13T17:57:28.556094Z"
    },
    {
      "dishId": 2,
      "id": 13,
      "rating": 4,
      "comment": "Ultimate, Reaching for the stars!",
      "author": "Rahat",
      "date": "2017-12-02T17:57:28.556094Z"
    },
    {
      "dishId": 2,
      "id": 14,
      "rating": 2,
      "comment": "It's your birthday, we're gonna party!",
      "author": "Rony",
      "date": "2019-12-02T17:57:28.556094Z"
    },
    {
      "dishId": 3,
      "id": 15,
      "rating": 5,
      "comment": "Imagine all the eatables, living in conFusion!",
      "author": "Shanto",
      "date": "2018-10-16T17:57:28.556094Z"
    },
    {
      "dishId": 3,
      "id": 16,
      "rating": 4,
      "comment": "Sends anyone to heaven, I wish I could get my mother-in-law to eat it!",
      "author": "Karim",
      "date": "2017-09-05T17:57:28.556094Z"
    },
    {
      "dishId": 3,
      "id": 17,
      "rating": 3,
      "comment": "Eat it, just eat it!",
      "author": "Moinul",
      "date": "2019-02-13T17:57:28.556094Z"
    },
    {
      "dishId": 3,
      "id": 18,
      "rating": 4,
      "comment": "Ultimate, Reaching for the stars!",
      "author": "Rahat",
      "date": "2017-12-02T17:57:28.556094Z"
    },
    {
      "dishId": 3,
      "id": 19,
      "rating": 2,
      "comment": "It's your birthday, we're gonna party!",
      "author": "Rony",
      "date": "2019-12-02T17:57:28.556094Z"
    },
    {
      "dishId": 0,
      "author": "Nahid",
      "rating": "4",
      "comment": "yammy",
      "data": "2021-06-27T01:03:58.980Z",
      "id": 20
    },
    {
      "dishId": 2,
      "author": "Wahid",
      "rating": "5",
      "comment": "testy",
      "data": "2021-06-27T01:06:12.909Z",
      "id": 21
    },
    {
      "dishId": 0,
      "author": "Wahid",
      "rating": "4",
      "comment": "adfefge",
      "data": "2021-06-27T01:11:36.371Z",
      "id": 22
    },
    {
      "dishId": 0,
      "author": "Wahid",
      "rating": "3",
      "comment": "xcvc",
      "id": 23
    },
    {
      "dishId": 0,
      "author": "jami",
      "rating": "4",
      "comment": "testy",
      "id": 24
    },
    {
      "dishId": 1,
      "author": "Wahid",
      "rating": "3",
      "comment": "sweet",
      "id": 25
    },
    {
      "dishId": 1,
      "author": "gSRH",
      "rating": "3",
      "comment": "dag",
      "id": 26
    },
    {
      "dishId": 0,
      "author": "Nahid",
      "rating": "5",
      "comment": "SDAFsag",
      "id": 27
    },
    {
      "dishId": 0,
      "author": "gSRH",
      "rating": "3",
      "comment": "aDASF",
      "id": 28
    },
    {
      "dishId": 0,
      "author": "Asif",
      "rating": "4",
      "comment": "Very Nice\n",
      "id": 29
    },
    {
      "dishId": 0,
      "author": "Jishat",
      "rating": "4",
      "comment": "asfdgsh",
      "id": 30
    },
    {
      "dishId": 3,
      "author": "Wahid",
      "rating": "4",
      "comment": "sfdfgjhjkjj",
      "id": 31
    },
    {
      "dishId": 2,
      "author": "Wahid",
      "rating": "5",
      "comment": "safsf",
      "id": 32
    }
  ],
  "feedback": [
    {
      "firstname": "sddsadf",
      "lastname": "ascasc",
      "telnum": "35346",
      "email": "wahid.cse38@gmail.com",
      "agree": true,
      "contactType": "Mobile",
      "message": "asdfsetget",
      "id": 1
    },
    {
      "firstname": "cascd",
      "lastname": "ascasc",
      "telnum": "35346",
      "email": "wahid.cse38@gmail.com",
      "agree": true,
      "contactType": "Mobile",
      "message": "etgrwyrway",
      "id": 2
    },
    {
      "firstname": "sddsadf",
      "lastname": "ascasc",
      "telnum": "35346",
      "email": "nahid@nahid.com",
      "agree": true,
      "contactType": "Mobile",
      "message": "sferyt",
      "id": 3
    },
    {
      "firstname": "sddsadf",
      "lastname": "ascasc",
      "email": "wahid.cse38@gmail.com",
      "telnum": "35346",
      "agree": true,
      "contactType": "Email",
      "message": "sdgfg",
      "id": 4
    },
    {
      "firstname": "wahidul",
      "lastname": "Islam",
      "email": "wahid.cse38@gmail.com",
      "telnum": "01813817063",
      "agree": true,
      "contactType": "Email",
      "message": "Nice",
      "id": 5
    },
    {
      "firstname": "cascd",
      "lastname": "adfdaf",
      "email": "nahid@nahid.com",
      "telnum": "13243254786",
      "agree": false,
      "contactType": "Mobile",
      "message": "EWHWJ",
      "id": 6
    },
    {
      "firstname": "sddsadf",
      "lastname": "ascasc",
      "telnum": "01813817063",
      "email": "wahid.cse38@gmail.com",
      "agree": true,
      "contactType": "Mobile",
      "message": "sadfghgj",
      "id": 7
    },
    {
      "firstname": "sddsadf",
      "lastname": "wahid",
      "telnum": "01813817063",
      "email": "wahid.cse38@gmail.com",
      "agree": false,
      "contactType": "Mobile",
      "message": "asdfghj",
      "id": 8
    },
    {
      "firstname": "sddsadf",
      "lastname": "sdvsdvsdv",
      "telnum": "13243254786",
      "email": "abc@gmail.com",
      "agree": true,
      "contactType": "Email",
      "message": "xzFzdgDH",
      "id": 9
    }
  ]
}